hictools/.DS_Store
hictools/__init__.py
hictools/chrommatrix.py
hictools/cli.py
hictools/compare.py
hictools/compartment.py
hictools/config.py
hictools/peaks.py
hictools/reconstruct.py
hictools/stripe.py
hictools/tad.py
hictools/hgserver/__init__.py
hictools/hgserver/cli.py
hictools/hgserver/monitor.py
hictools/hgserver/server.py
hictools/hgserver/store.py
hictools/hgserver/ui/index.html
hictools/utils/.DS_Store
hictools/utils/__init__.py
hictools/utils/cnumtools.cpp
hictools/utils/cnumtools.cpython-38-x86_64-linux-gnu.so
hictools/utils/io.py
hictools/utils/numtools.py
hictools/utils/utils.py
test/__init__.py
test/conftest.py
test/test_api.py
test/test_io.py
test/test_utils.py
hictools-0.1.4.4.dist-info/LICENSE
hictools-0.1.4.4.dist-info/METADATA
hictools-0.1.4.4.dist-info/WHEEL
hictools-0.1.4.4.dist-info/entry_points.txt
hictools-0.1.4.4.dist-info/top_level.txt
hictools-0.1.4.4.dist-info/RECORD
