Metadata-Version: 2.1
Name: hictools
Version: 0.1.4.4
Summary: Tools for handling hic data
Home-page: https://github.com/zhqu1148980644/hictools
Author: BAKEZQ
Author-email: zhongquan789@gmail.com
License: MIT
Platform: UNKNOWN
Classifier: License :: OSI Approved :: MIT License
Classifier: Programming Language :: Python :: 3
Classifier: Programming Language :: Python :: 3.8
Classifier: Programming Language :: Python :: Implementation :: CPython
Classifier: Programming Language :: Python :: Implementation :: PyPy
Requires-Python: >=3.7.0
Requires-Dist: setuptools
Requires-Dist: colorama
Requires-Dist: Click
Requires-Dist: scipy
Requires-Dist: numpy
Requires-Dist: pandas
Requires-Dist: sklearn
Requires-Dist: statsmodels
Requires-Dist: scikit-learn
Requires-Dist: cooler
Requires-Dist: uvloop
Requires-Dist: ujson
Requires-Dist: watchgod
Requires-Dist: SQLAlchemy
Requires-Dist: databases
Requires-Dist: uvicorn
Requires-Dist: fastapi
Requires-Dist: starlette
Requires-Dist: slugid
Requires-Dist: aiosqlite
Requires-Dist: clodius
Provides-Extra: test
Requires-Dist: mypy ; extra == 'test'
Requires-Dist: pytest ; extra == 'test'
